samcell1_0_napari-0.1.0.dist-info/licenses/LICENSE
samcell_napari/__init__.py
samcell_napari/__main__.py
samcell_napari/_dock_widget.py
samcell_napari/_sample_data.py
samcell_napari/icon.svg
samcell_napari/model.py
samcell_napari/napari.yaml
samcell_napari/pipeline.py
samcell_napari/slidingWindow.py
samcell1_0_napari-0.1.0.dist-info/METADATA
samcell1_0_napari-0.1.0.dist-info/WHEEL
samcell1_0_napari-0.1.0.dist-info/entry_points.txt
samcell1_0_napari-0.1.0.dist-info/top_level.txt
samcell1_0_napari-0.1.0.dist-info/RECORD
