Metadata-Version: 2.4
Name: samcell1.0-napari
Version: 0.1.0
Summary: A napari plugin for cell segmentation with SAMCell 1.0
Home-page: https://github.com/saahilsanganeriya/samcell-napari
Author: Saahil Sanganeriya
Author-email: saahilsanganeria666@gmail.com
Project-URL: Bug Tracker, https://github.com/saahilsanganeriya/samcell-napari/issues
Classifier: Programming Language :: Python :: 3
Classifier: Programming Language :: Python :: 3.8
Classifier: Programming Language :: Python :: 3.9
Classifier: Programming Language :: Python :: 3.10
Classifier: License :: OSI Approved :: MIT License
Classifier: Operating System :: OS Independent
Classifier: Framework :: napari
Classifier: Intended Audience :: Science/Research
Classifier: Topic :: Scientific/Engineering :: Bio-Informatics
Classifier: Topic :: Scientific/Engineering :: Image Processing
Requires-Python: >=3.8
License-File: LICENSE
Requires-Dist: napari>=0.4.14
Requires-Dist: numpy
Requires-Dist: torch>=1.9
Requires-Dist: transformers>=4.20.0
Requires-Dist: scikit-image
Requires-Dist: opencv-python
Dynamic: license-file
